Metadata-Version: 2.1
Name: django-ndarray
Version: 0.0.2
Summary: Numpy n-dimensional field for Django.
Home-page: http://github.com/sorl/django-ndarray
Author: Mikko Hellsing
Author-email: mikko@sumsum.se
License: ICS
Platform: UNKNOWN
Classifier: Development Status :: 5 - Production/Stable
Classifier: Intended Audience :: Developers
Classifier: License :: OSI Approved :: ISC License (ISCL)
Classifier: Operating System :: OS Independent
Classifier: Programming Language :: Python
Classifier: Programming Language :: Python :: 3.5
Classifier: Programming Language :: Python :: 3.6
Classifier: Programming Language :: Python :: 3.7
Classifier: Framework :: Django
